ApiProxy/__init__.py
ApiProxy/proxy.py
ApiProxy/dependencies/apiproxy-linux
ApiProxy/dependencies/apiproxy-macos
ApiProxy/dependencies/apiproxy.exe
ApiProxy-0.0.5.dist-info/LICENSE
ApiProxy-0.0.5.dist-info/METADATA
ApiProxy-0.0.5.dist-info/WHEEL
ApiProxy-0.0.5.dist-info/top_level.txt
ApiProxy-0.0.5.dist-info/RECORD
