Metadata-Version: 2.1
Name: ApiProxy
Version: 0.0.5
Summary: Proxy server, used for browser proxy access, supports dynamic proxy switching
Home-page: https://github.com/test741123/ApiProxy
Author: hesheng
Author-email: 1296602221@qq.com
License: MIT
Classifier: License :: OSI Approved :: MIT License
Classifier: Operating System :: Unix
Classifier: Operating System :: MacOS :: MacOS X
Classifier: Operating System :: Microsoft :: Windows
Classifier: Programming Language :: Python
Classifier: Programming Language :: Python :: 3
Requires-Python: >=3.7
License-File: LICENSE
Requires-Dist: requests >=2.28.1
